hellimath/__init__.py
hellimath/algebra.py
hellimath/calculus.py
hellimath/geometry.py
hellimath/linear_algebra.py
hellimath/number_theory.py
hellimath/statistics.py
hellimath/trigonometry.py
hellimath-1.0.0.dist-info/licenses/LICENSE.mit
hellimath-1.0.0.dist-info/METADATA
hellimath-1.0.0.dist-info/WHEEL
hellimath-1.0.0.dist-info/top_level.txt
hellimath-1.0.0.dist-info/RECORD
